Workbook
Name Cobertura_Stock: Operaciones!$K$2:$K$9
Name Incremento_Costo: Parametros!$B$3
Name Ingresos_Base: Operaciones!$G$2:$G$9
Name Margen_Base: Operaciones!$I$2:$I$9
Name Margen_Escenario: Operaciones!$O$2:$O$9
Name Tasa_Descuento: Parametros!$B$2
Name Unidades_Vendidas: Operaciones!$C$2:$C$9

Sheet Operaciones
A1: Código | B1: Producto | C1: Unidades vendidas | D1: Precio unitario S/ | E1: Costo unitario S/ | F1: Stock final | G1: Ingresos | H1: Costo de ventas | I1: Margen bruto | J1: Margen bruto porcentual | K1: Cobertura estimada en meses | L1: Precio con descuento | M1: Costo ajustado | N1: Ingresos del escenario | O1: Margen bruto del escenario | P1: Variación del margen
A2: P001 | B2: Laptop | C2: 12 | D2: 2500 | E2: 2150 | F2: 4 | G2: =C2*D2 -> 30000 | H2: =C2*E2 -> 25800 | I2: =G2-H2 -> 4200 | J2: =I2/G2 -> 0.14 | K2: =F2/C2 -> 0.33333333 | L2: =D2*(1-Parametros!$B$2) -> 2375 | M2: =E2*(1+Parametros!$B$3) -> 2322 | N2: =C2*L2 -> 28500 | O2: =N2-C2*M2 -> 636 | P2: =O2-I2 -> -3564
A3: P002 | B3: Monitor | C3: 25 | D3: 650 | E3: 480 | F3: 10 | G3: =C3*D3 -> 16250 | H3: =C3*E3 -> 12000 | I3: =G3-H3 -> 4250 | J3: =I3/G3 -> 0.26153846 | K3: =F3/C3 -> 0.4 | L3: =D3*(1-Parametros!$B$2) -> 617.5 | M3: =E3*(1+Parametros!$B$3) -> 518.4 | N3: =C3*L3 -> 15437.5 | O3: =N3-C3*M3 -> 2477.5 | P3: =O3-I3 -> -1772.5
A4: P003 | B4: Teclado | C4: 80 | D4: 85 | E4: 45 | F4: 20 | G4: =C4*D4 -> 6800 | H4: =C4*E4 -> 3600 | I4: =G4-H4 -> 3200 | J4: =I4/G4 -> 0.47058824 | K4: =F4/C4 -> 0.25 | L4: =D4*(1-Parametros!$B$2) -> 80.75 | M4: =E4*(1+Parametros!$B$3) -> 48.6 | N4: =C4*L4 -> 6460 | O4: =N4-C4*M4 -> 2572 | P4: =O4-I4 -> -628
A5: P004 | B5: Mouse | C5: 120 | D5: 45 | E5: 22 | F5: 35 | G5: =C5*D5 -> 5400 | H5: =C5*E5 -> 2640 | I5: =G5-H5 -> 2760 | J5: =I5/G5 -> 0.51111111 | K5: =F5/C5 -> 0.29166667 | L5: =D5*(1-Parametros!$B$2) -> 42.75 | M5: =E5*(1+Parametros!$B$3) -> 23.76 | N5: =C5*L5 -> 5130 | O5: =N5-C5*M5 -> 2278.8 | P5: =O5-I5 -> -481.2
A6: P005 | B6: Impresora | C6: 10 | D6: 900 | E6: 730 | F6: 18 | G6: =C6*D6 -> 9000 | H6: =C6*E6 -> 7300 | I6: =G6-H6 -> 1700 | J6: =I6/G6 -> 0.18888889 | K6: =F6/C6 -> 1.8 | L6: =D6*(1-Parametros!$B$2) -> 855 | M6: =E6*(1+Parametros!$B$3) -> 788.4 | N6: =C6*L6 -> 8550 | O6: =N6-C6*M6 -> 666 | P6: =O6-I6 -> -1034
A7: P006 | B7: SSD | C7: 40 | D7: 220 | E7: 150 | F7: 12 | G7: =C7*D7 -> 8800 | H7: =C7*E7 -> 6000 | I7: =G7-H7 -> 2800 | J7: =I7/G7 -> 0.31818182 | K7: =F7/C7 -> 0.3 | L7: =D7*(1-Parametros!$B$2) -> 209 | M7: =E7*(1+Parametros!$B$3) -> 162 | N7: =C7*L7 -> 8360 | O7: =N7-C7*M7 -> 1880 | P7: =O7-I7 -> -920
A8: P007 | B8: Memoria RAM | C8: 50 | D8: 160 | E8: 105 | F8: 15 | G8: =C8*D8 -> 8000 | H8: =C8*E8 -> 5250 | I8: =G8-H8 -> 2750 | J8: =I8/G8 -> 0.34375 | K8: =F8/C8 -> 0.3 | L8: =D8*(1-Parametros!$B$2) -> 152 | M8: =E8*(1+Parametros!$B$3) -> 113.4 | N8: =C8*L8 -> 7600 | O8: =N8-C8*M8 -> 1930 | P8: =O8-I8 -> -820
A9: P008 | B9: Cámara web | C9: 15 | D9: 140 | E9: 90 | F9: 45 | G9: =C9*D9 -> 2100 | H9: =C9*E9 -> 1350 | I9: =G9-H9 -> 750 | J9: =I9/G9 -> 0.35714286 | K9: =F9/C9 -> 3 | L9: =D9*(1-Parametros!$B$2) -> 133 | M9: =E9*(1+Parametros!$B$3) -> 97.2 | N9: =C9*L9 -> 1995 | O9: =N9-C9*M9 -> 537 | P9: =O9-I9 -> -213
A11: celdas de colores = entradas editables

Sheet Parametros
A1: Parámetro | B1: Valor
A2: Descuento comercial | B2: 0.05
A3: Incremento del costo | B3: 0.08

Sheet Resumen
A1: Indicador | B1: Resultado | C1: Producto
A2: Cantidad de registros numéricos de unidades vendidas | B2: =COUNT(Unidades_Vendidas) -> 8
A3: Total de unidades vendidas | B3: =SUM(Unidades_Vendidas) -> 352
A4: Total de ingresos | B4: =SUM(Operaciones!G2:G9) -> 86350
A5: Total del costo de ventas | B5: =SUM(Operaciones!H2:H9) -> 63940
A6: Total del margen bruto | B6: =SUM(Operaciones!I2:I9) -> 22410
A7: Promedio de unidades vendidas por producto | B7: =AVERAGE(Unidades_Vendidas) -> 44
A8: Mayor ingreso por producto | B8: =MAX(Ingresos_Base) -> 30000 | C8: Laptop
A9: Menor ingreso por producto | B9: =MIN(Operaciones!G2:G9) -> 2100 | C9: Cámara web
A10: Mayor margen bruto por producto | B10: =MAX(Operaciones!I2:I9) -> 4250 | C10: Monitor
A11: Menor cobertura estimada | B11: =MIN(Cobertura_Stock) -> 0.25 | C11: Teclado
A12: Mayor cobertura estimada | B12: =MAX(Operaciones!K2:K9) -> 3 | C12: Cámara web
A13: Promedio de los porcentajes de margen por producto | B13: =AVERAGE(Operaciones!J2:J9) -> 0.32390017
A14: Margen bruto porcentual global | B14: =B6/B4 -> 0.25952519
A16: Comprobación: ingresos − costo | B16: =B4-B5 -> 22410
A18: Ingresos totales del escenario | B18: =SUM(Operaciones!N2:N9) -> 82032.5
A19: Margen bruto total del escenario | B19: =SUM(Margen_Escenario) -> 12977.3
A20: Variación del margen bruto total | B20: =B19-B6 -> -9432.7
A21: Margen bruto porcentual global del escenario | B21: =B19/B18 -> 0.15819706
A23: Descuento aplicado | B23: =Tasa_Descuento -> 0.05
A24: Incremento del costo aplicado | B24: =Incremento_Costo -> 0.08

Sheet Escenarios
A2: Incremento del costo/ Descuento | B2: 0 | C2: 0.05 | D2: 0.1 | E2: 0.15
A3: 0 | B3: =Operaciones!$C$2*(Operaciones!$D$2*(1-B$2)-Operaciones!$E$2*(1+$A3)) -> 4200 | C3: =Operaciones!$C$2*(Operaciones!$D$2*(1-C$2)-Operaciones!$E$2*(1+$A3)) -> 2700 | D3: =Operaciones!$C$2*(Operaciones!$D$2*(1-D$2)-Operaciones!$E$2*(1+$A3)) -> 1200 | E3: =Operaciones!$C$2*(Operaciones!$D$2*(1-E$2)-Operaciones!$E$2*(1+$A3)) -> -300
A4: 0.05 | B4: =Operaciones!$C$2*(Operaciones!$D$2*(1-B$2)-Operaciones!$E$2*(1+$A4)) -> 2910 | C4: =Operaciones!$C$2*(Operaciones!$D$2*(1-C$2)-Operaciones!$E$2*(1+$A4)) -> 1410 | D4: =Operaciones!$C$2*(Operaciones!$D$2*(1-D$2)-Operaciones!$E$2*(1+$A4)) -> -90 | E4: =Operaciones!$C$2*(Operaciones!$D$2*(1-E$2)-Operaciones!$E$2*(1+$A4)) -> -1590
A5: 0.1 | B5: =Operaciones!$C$2*(Operaciones!$D$2*(1-B$2)-Operaciones!$E$2*(1+$A5)) -> 1620 | C5: =Operaciones!$C$2*(Operaciones!$D$2*(1-C$2)-Operaciones!$E$2*(1+$A5)) -> 120 | D5: =Operaciones!$C$2*(Operaciones!$D$2*(1-D$2)-Operaciones!$E$2*(1+$A5)) -> -1380 | E5: =Operaciones!$C$2*(Operaciones!$D$2*(1-E$2)-Operaciones!$E$2*(1+$A5)) -> -2880
A6: 0.15 | B6: =Operaciones!$C$2*(Operaciones!$D$2*(1-B$2)-Operaciones!$E$2*(1+$A6)) -> 330 | C6: =Operaciones!$C$2*(Operaciones!$D$2*(1-C$2)-Operaciones!$E$2*(1+$A6)) -> -1170 | D6: =Operaciones!$C$2*(Operaciones!$D$2*(1-D$2)-Operaciones!$E$2*(1+$A6)) -> -2670 | E6: =Operaciones!$C$2*(Operaciones!$D$2*(1-E$2)-Operaciones!$E$2*(1+$A6)) -> -4170
A8: Mayor margen | B8: =MAX(B3:E6) -> 4200
A9: Menor margen | B9: =MIN(B3:E6) -> -4170
A11: Mayor margen: incremento 0 % y descuento 0 %
A12: Menor margen: incremento 15 % y descuento 15 %
A13: Celdas en rojo = combinaciones con margen negativo

Sheet Decisiones
A1: Decisiones y análisis
A2: Preguntas | B2: Respuesta
A3: Aplica CONTAR a los códigos y a las unidades vendidas. Explica la diferencia. | B3: CONTAR en los códigos da 0 porque son texto. En las unidades da 8 porque son números. CONTAR solo cuenta valores numéricos.
A4: ¿Por qué el promedio de los porcentajes de margen puede diferir del porcentaje global? | B4: El promedio (32.39 %) da el mismo peso a cada producto. El global (25.95 %) divide el margen total entre los ingresos totales, así que pesan más los productos que más se venden, como la Laptop (14 %).
A5: ¿Qué ocurriría al copiar las fórmulas si las referencias a los parámetros fueran relativas? | B5: Al copiar la fórmula hacia abajo, la referencia se movería a B3, B4... y tomaría datos equivocados o celdas vacías. El descuento y el costo ya no serían los de los parámetros.
A6: ¿Cómo facilitan los nombres la lectura de las fórmulas? | B6: Permiten leer =SUMA(Unidades_Vendidas) en vez de =SUMA(Operaciones!C2:C9). Se entiende qué dato se usa, hay menos errores de rango y es más fácil revisar.
A8: Análisis
A9: ¿Qué producto genera mayores ingresos? | B9: La Laptop, con S/ 30,000.00.
A10: ¿Qué producto genera mayor margen bruto en soles? | B10: El Monitor, con S/ 4,250.00 (la Laptop queda muy cerca, con S/ 4,200.00).
A11: ¿Qué producto presenta mayor margen bruto porcentual? | B11: El Mouse, con 51.11 %.
A12: ¿Por qué estos indicadores pueden señalar productos diferentes? | B12: Los ingresos dependen del precio y del volumen. El margen en soles es ingreso menos costo, y el margen % mide la ganancia sobre el ingreso. La Laptop vende caro pero con 14.00 %. El Mouse es barato pero con 51.11 %.
A13: ¿Qué producto evaluarías primero para reposición y cuál por posible acumulación? Fundamenta. | B13: Para reposición, el Teclado: su cobertura es de 0.25 meses (20 de stock frente a 80 vendidas). Por posible acumulación, la Cámara web: su cobertura es de 3.00 meses (45 de stock frente a 15 vendidas).
A14: ¿Cómo afecta el escenario comercial al margen bruto total? | B14: El margen bruto total baja de S/ 22,410.00 a S/ 12,977.30 (variación de -S/ 9,432.70). El margen global baja de 25.95 % a 15.82 %.
A15: ¿Qué combinación de la matriz desaconsejarías y por qué? | B15: Descuento 15 % con incremento de costo 15 %: da -S/ 4,170.00, la mayor pérdida. En la matriz hay 8 combinaciones con margen negativo.
A16: ¿Qué información falta para determinar cantidades de compra? | B16: Cómo reaccionaría la demanda al descuento, los gastos operativos, los tiempos de reposición del proveedor, las ventas por mes y el presupuesto de compra.
A18: Recomendación gerencial
A19: Recomendación (150 a 200 palabras) | B19: Se recomienda priorizar la reposición del Teclado y mantener los precios actuales, sin aplicar el descuento general del 5 % por ahora. El Teclado tiene la menor cobertura (0.25 meses) y un margen bruto de 47.06 %, por lo que un quiebre de stock afectaría ventas rentables. El modelo base genera ingresos por S/ 86,350.00 y un margen bruto de S/ 22,410.00 (25.95 %). En cambio, el escenario comercial, con 5 % de descuento y 8 % de aumento del costo, reduce los ingresos a S/ 82,032.50 y el margen a S/ 12,977.30 (15.82 %), una caída de S/ 9,432.70. Además, la Cámara web acumula 3.00 meses de cobertura, por lo que conviene evitar nuevas compras. Para decidir las cantidades de compra se necesitan datos adicionales: la reacción de la demanda al descuento y los plazos de reposición del proveedor. Una limitación es que el análisis usa un solo mes, mantiene constantes las unidades vendidas y no incluye gastos operativos, por lo que el margen bruto no equivale a la utilidad neta.
A21: Reflexión final
A22: ¿Qué error de fórmula podría producir una decisión equivocada? | B22: Usar un rango incompleto (por ejemplo C2:C8 en lugar de C2:C9) o una referencia relativa donde debía ser absoluta. El resultado se ve normal pero es incorrecto, y podría llevar a comprar o descontar los productos equivocados.
A23: ¿Qué ventaja aportan las referencias y los nombres cuando cambia un dato? | B23: Todo se actualiza automáticamente sin reescribir fórmulas, y los nombres hacen que las fórmulas se lean y se revisen con más facilidad.
A24: ¿Qué protege tu archivo y qué limitaciones tienen esas protecciones? | B24: Protege fórmulas, hojas y estructura contra cambios accidentales: bloquea celdas, oculta fórmulas e impide renombrar hojas. No cifra el archivo: la contraseña es académica y puede quitarse con herramientas, y cualquiera con el archivo puede copiarlo.
A26: Vinculación con el trabajo final
A27: Organizacion o procesos | B27: Un colegio, en el proceso de control de asistencia del aula de innovación, con una aplicación en Excel con macros y VBA.
A28: Decision que requiere apoyo | B28: A qué estudiantes o secciones darles seguimiento por inasistencias y cómo programar el uso del aula según la asistencia.
A29: Cinco datos necesarios | B29: Código del estudiante, grado y sección, fecha y horario de la sesión, estado de asistencia (asistió, tardanza o faltó) y justificación de la falta.
A30: Dos indicadores en excel | B30: Porcentaje de asistencia por estudiante y por sección (asistencias ÷ sesiones) y total de inasistencias acumuladas, con alerta al superar un límite.

Sheet Evidencias
A1: Evidencia 1: fórmula con referencias relativas (G2).
A30: Evidencia 2: fórmula con referencias absolutas (L2).
A62: Evidencia 3: fórmula inicial de la matriz con referencias mixtas (Escenarios, celda B3)
A100: Evidencia 4: Administrador de nombres (7 nombres definidos con ámbito de libro)
A144: Evidencia 5: intento de modificar una fórmula bloqueada (Operaciones, G2)
A176: Evidencia 6: celda con resultado visible y fórmula oculta (Operaciones, G2)
